azure/mgmt/confluent/__init__.py
azure/mgmt/confluent/_configuration.py
azure/mgmt/confluent/_confluent_management_client.py
azure/mgmt/confluent/_patch.py
azure/mgmt/confluent/_serialization.py
azure/mgmt/confluent/_vendor.py
azure/mgmt/confluent/_version.py
azure/mgmt/confluent/py.typed
azure/mgmt/confluent/aio/__init__.py
azure/mgmt/confluent/aio/_configuration.py
azure/mgmt/confluent/aio/_confluent_management_client.py
azure/mgmt/confluent/aio/_patch.py
azure/mgmt/confluent/aio/operations/__init__.py
azure/mgmt/confluent/aio/operations/_access_operations.py
azure/mgmt/confluent/aio/operations/_marketplace_agreements_operations.py
azure/mgmt/confluent/aio/operations/_organization_operations.py
azure/mgmt/confluent/aio/operations/_organization_operations_operations.py
azure/mgmt/confluent/aio/operations/_patch.py
azure/mgmt/confluent/aio/operations/_validations_operations.py
azure/mgmt/confluent/models/__init__.py
azure/mgmt/confluent/models/_confluent_management_client_enums.py
azure/mgmt/confluent/models/_models_py3.py
azure/mgmt/confluent/models/_patch.py
azure/mgmt/confluent/operations/__init__.py
azure/mgmt/confluent/operations/_access_operations.py
azure/mgmt/confluent/operations/_marketplace_agreements_operations.py
azure/mgmt/confluent/operations/_organization_operations.py
azure/mgmt/confluent/operations/_organization_operations_operations.py
azure/mgmt/confluent/operations/_patch.py
azure/mgmt/confluent/operations/_validations_operations.py
azure_mgmt_confluent-2.1.0.dist-info/LICENSE
azure_mgmt_confluent-2.1.0.dist-info/METADATA
azure_mgmt_confluent-2.1.0.dist-info/WHEEL
azure_mgmt_confluent-2.1.0.dist-info/top_level.txt
azure_mgmt_confluent-2.1.0.dist-info/RECORD
